{
  "username": "Karmanya03",
  "updated": "07 May 2026 11:26 UTC",
  "totals": {
    "repos": 39,
    "stars": 11,
    "forks": 0,
    "active_90": 12,
    "unique_languages": 12,
    "commits": 518,
    "prs": 7,
    "issues": 0
  },
  "top_languages": [
    [
      "Rust",
      5035353
    ],
    [
      "HTML",
      278259
    ],
    [
      "JavaScript",
      270020
    ],
    [
      "CSS",
      247529
    ],
    [
      "Python",
      222002
    ],
    [
      "Shell",
      47099
    ]
  ]
}