{
  "username": "Karmanya03",
  "updated": "15 Jun 2026 18:08 UTC",
  "totals": {
    "repos": 42,
    "stars": 24,
    "forks": 1,
    "active_90": 12,
    "unique_languages": 13,
    "commits": 664,
    "prs": 7,
    "issues": 0
  },
  "top_languages": [
    [
      "Rust",
      9980855
    ],
    [
      "Python",
      491676
    ],
    [
      "JavaScript",
      362595
    ],
    [
      "HTML",
      351887
    ],
    [
      "CSS",
      247529
    ],
    [
      "Shell",
      54410
    ]
  ]
}